kaal/__init__.py
kaal/hello.py
kaal/test.py
kaal/trainer/__init__.py
kaal/trainer/trainer.py
kaal/utils/__init__.py
kaal/utils/preprocessing.py
kaal-1.1.0.dist-info/METADATA
kaal-1.1.0.dist-info/WHEEL
kaal-1.1.0.dist-info/top_level.txt
kaal-1.1.0.dist-info/RECORD
