Metadata-Version: 2.1
Name: kaal
Version: 1.1.0
Summary: Coming soon
Author: Debangan Mishra
Author-email: Debangan <debangan.coding@gmail.com>
